netbox_counterparties/__init__.py
netbox_counterparties/api/__init__.py
netbox_counterparties/api/nested_serializers.py
netbox_counterparties/api/serializers.py
netbox_counterparties/api/urls.py
netbox_counterparties/api/views.py
netbox_counterparties/filtersets.py
netbox_counterparties/forms.py
netbox_counterparties/migrations/__init__.py
netbox_counterparties/models.py
netbox_counterparties/navigation.py
netbox_counterparties/search.py
netbox_counterparties/tables.py
netbox_counterparties/template_content.py
netbox_counterparties/templates/netbox_counterparties/counterparty.html
netbox_counterparties/templates/netbox_counterparties/counterpartyassignment_edit.html
netbox_counterparties/templates/netbox_counterparties/counterpartygroup.html
netbox_counterparties/templates/netbox_counterparties/counterpartyrole.html
netbox_counterparties/templates/netbox_counterparties/object_counterparties.html
netbox_counterparties/urls.py
netbox_counterparties/views.py
netbox_counterparties-0.1.1.dist-info/LICENSE
netbox_counterparties-0.1.1.dist-info/METADATA
netbox_counterparties-0.1.1.dist-info/WHEEL
netbox_counterparties-0.1.1.dist-info/RECORD
